etl_script/__init__.py
etl_script/cli.py
etl_script/inp.py
etl_script/pushtoES.py
etl_script/scriptConst.py
sfapmetl-0.2.6.dist-info/METADATA
sfapmetl-0.2.6.dist-info/WHEEL
sfapmetl-0.2.6.dist-info/entry_points.txt
sfapmetl-0.2.6.dist-info/top_level.txt
sfapmetl-0.2.6.dist-info/RECORD
