Metadata-Version: 2.1
Name: sfapmetl
Version: 0.2.6
Summary: etlReport script
Home-page: https://github.com/ruchira-dot-rao/sf-apm-etl
Author: dummy
Author-email: ruchira.rao@maplelabs.com
License: BSD
Platform: any
Classifier: Development Status :: 4 - Beta
Classifier: Environment :: Console
Classifier: Intended Audience :: Developers
Classifier: License :: OSI Approved :: BSD License
Classifier: Operating System :: POSIX
Classifier: Operating System :: MacOS
Classifier: Operating System :: Unix
Classifier: Operating System :: Microsoft :: Windows
Classifier: Programming Language :: Python
Classifier: Programming Language :: Python :: 2
Classifier: Programming Language :: Python :: 3
Classifier: Topic :: Software Development :: Libraries :: Python Modules
Requires-Dist: click
Requires-Dist: elasticsearch
Requires-Dist: schedule
Requires-Dist: requests
Requires-Dist: pycrypto
Requires-Dist: PyYAML
Requires-Dist: urllib3
